[
  {
    "inputs": [],
    "name": "Position__InvalidOrderType",
    "type": "error"
  },
  {
    "inputs": [
      {
        "internalType": "UD60x18",
        "name": "currentBalance",
        "type": "uint256"
      },
      {
        "internalType": "SD59x18",
        "name": "amount",
        "type": "int256"
      }
    ],
    "name": "Position__InvalidPositionUpdate",
    "type": "error"
  },
  {
    "inputs": [
      {
        "internalType": "UD60x18",
        "name": "lower",
        "type": "uint256"
      },
      {
        "internalType": "UD60x18",
        "name": "upper",
        "type": "uint256"
      }
    ],
    "name": "Position__LowerGreaterOrEqualUpper",
    "type": "error"
  }
]
